NPi/CHANGELOG.txt
NPi/LICENSE
NPi/README.md
NPi/_GPIO.cpython-36m-arm-linux-gnueabihf.so
NPi/__init__.py
NPi/GPIO/__init__.py
NPi.GPIO-0.5.8.6.dist-info/LICENSE
NPi.GPIO-0.5.8.6.dist-info/METADATA
NPi.GPIO-0.5.8.6.dist-info/WHEEL
NPi.GPIO-0.5.8.6.dist-info/top_level.txt
NPi.GPIO-0.5.8.6.dist-info/RECORD
