Metadata-Version: 2.1
Name: NPi.GPIO
Version: 0.5.8.6
Summary: A module to control NanoPi GPIO channels
Home-page: https://github.com/Tungsteno74/NPi.GPIO
Author: Tungsteno
Author-email: contacts00-npigpio@yahoo.it
License: MIT
Keywords: NanoPi GPIO
Platform: UNKNOWN
Classifier: Development Status :: 5 - Production/Stable
Classifier: Operating System :: POSIX :: Linux
Classifier: License :: OSI Approved :: MIT License
Classifier: Intended Audience :: Developers
Classifier: Programming Language :: Python :: 2.7
Classifier: Programming Language :: Python :: 3
Classifier: Topic :: Software Development
Classifier: Topic :: Home Automation
Classifier: Topic :: System :: Hardware
